contrib_checker/__init__.py
contrib_checker/cli.py
contrib_checker/core.py
contrib_checker/github.py
contrib_checker/gitlab.py
contrib_checker-1.0.0.dist-info/licenses/LICENSE
contrib_checker-1.0.0.dist-info/METADATA
contrib_checker-1.0.0.dist-info/WHEEL
contrib_checker-1.0.0.dist-info/entry_points.txt
contrib_checker-1.0.0.dist-info/top_level.txt
contrib_checker-1.0.0.dist-info/RECORD
