Metadata-Version: 2.4
Name: contrib-checker
Version: 1.0.0
Summary: Check if code contributors are properly listed in metadata files such as CITATION.cff and codemeta.json based on the git history
Author-email: Thomas Vuillaume <thomas.vuillaume@lapp.in2p3.fr>
License: MIT
Project-URL: Homepage, https://github.com/vuillaut/contrib-checker
Project-URL: Repository, https://github.com/vuillaut/contrib-checker
Project-URL: Issues, https://github.com/vuillaut/contrib-checker/issues
Keywords: git,contributors,citation,metadata,github-actions,gitlab-ci
Classifier: Development Status :: 5 - Production/Stable
Classifier: Intended Audience :: Developers
Classifier: Operating System :: OS Independent
Classifier: Programming Language :: Python :: 3
Classifier: Topic :: Software Development :: Quality Assurance
Classifier: Topic :: Software Development :: Version Control :: Git
Classifier: Topic :: Documentation
Requires-Python: >=3.8
License-File: LICENSE
Requires-Dist: pyyaml>=5.4.0
Requires-Dist: requests>=2.25.0
Provides-Extra: dev
Requires-Dist: pytest>=6.0; extra == "dev"
Requires-Dist: pytest-cov; extra == "dev"
Requires-Dist: black; extra == "dev"
Requires-Dist: isort; extra == "dev"
Requires-Dist: flake8; extra == "dev"
Dynamic: license-file
